{
    "backend": "django",
    "db_name": "",
    "db_pass": "",
    "db_type": "mysql",
    "db_user": "",
    "dbms": "1",
    "description": "generated product",
    "design": "datta-able",
    "docker": "0",
    "err_code": 0,
    "frontend": "",
    "heroku": "0",
    "pattern": "mvc",
    "pro": "0",
    "task_id": "a822fc9c-ed7c-40e9-a828-850a3b47fc55",
    "task_info": "Upload Sources [0%] - 163 files",
    "task_output": "a822fc9c-ed7c-40e9-a828-850a3b47fc55.zip",
    "task_result": "SUCCESS",
    "task_state": "RUNNING",
    "task_ts_end": "2024-03-18-17-29-58",
    "task_ts_start": "2024-03-18-17-29-57"
}